semistructuredtxt2df/__init__.py
semistructuredtxt2df/main.py
semistructuredtxt2df-0.0.8.dist-info/LICENSE
semistructuredtxt2df-0.0.8.dist-info/METADATA
semistructuredtxt2df-0.0.8.dist-info/WHEEL
semistructuredtxt2df-0.0.8.dist-info/top_level.txt
semistructuredtxt2df-0.0.8.dist-info/RECORD
