Metadata-Version: 2.1
Name: semistructuredtxt2df
Version: 0.0.8
Summary: Reads a text file that has varying numbers of headers (e.g., when skiprows) and columns and returns a pandas DataFrame object.
Home-page: https://github.com/iiokentaro/semistructuredtxt2df
Author: iiokentaro
Author-email: 
License: BSD 3
License-File: LICENSE
Requires-Dist: pandas
